thor2timesketch/__init__.py
thor2timesketch/__main__.py
thor2timesketch/constants.py
thor2timesketch/exceptions.py
thor2timesketch/cli/__init__.py
thor2timesketch/cli/controller.py
thor2timesketch/config/__init__.py
thor2timesketch/config/console_config.py
thor2timesketch/config/default_filter.yaml
thor2timesketch/config/filter_audit.py
thor2timesketch/config/filter_creator.py
thor2timesketch/config/filter_findings.py
thor2timesketch/config/yaml_config_reader.py
thor2timesketch/input/__init__.py
thor2timesketch/input/file_validator.py
thor2timesketch/input/json_reader.py
thor2timesketch/input/json_validator.py
thor2timesketch/mappers/__init__.py
thor2timesketch/mappers/json_log_version.py
thor2timesketch/mappers/mapped_event.py
thor2timesketch/mappers/mapper_json_audit.py
thor2timesketch/mappers/mapper_json_audit_findings.py
thor2timesketch/mappers/mapper_json_audit_info.py
thor2timesketch/mappers/mapper_json_base.py
thor2timesketch/mappers/mapper_json_v1.py
thor2timesketch/mappers/mapper_json_v2.py
thor2timesketch/mappers/mapper_json_v3.py
thor2timesketch/mappers/mapper_loader.py
thor2timesketch/output/__init__.py
thor2timesketch/output/file_writer.py
thor2timesketch/output/output_writer.py
thor2timesketch/output/ts_ingest.py
thor2timesketch/transformation/__init__.py
thor2timesketch/transformation/json_transformer.py
thor2timesketch/transformation/pretransformation_processor.py
thor2timesketch/utils/__init__.py
thor2timesketch/utils/audit_events_extractor.py
thor2timesketch/utils/audit_timestamp_extractor.py
thor2timesketch/utils/datetime_field.py
thor2timesketch/utils/json_flattener.py
thor2timesketch/utils/normalizer.py
thor2timesketch/utils/progress_bar.py
thor2timesketch/utils/regex_timestamp_extractor.py
thor2timesketch/utils/thor_finding_id.py
thor2timesketch/utils/timestamp_extractor.py
thor2timesketch-0.1.6.dist-info/METADATA
thor2timesketch-0.1.6.dist-info/WHEEL
thor2timesketch-0.1.6.dist-info/entry_points.txt
thor2timesketch-0.1.6.dist-info/licenses/LICENSE
thor2timesketch-0.1.6.dist-info/RECORD
