Metadata-Version: 2.4
Name: thor2timesketch
Version: 0.1.6
Summary: Convert THOR security scanner logs to Timesketch format
Project-URL: Homepage, https://github.com/NextronSystems/thor2timesketch.git
Project-URL: Issues, https://github.com/NextronSystems/thor2timesketch/issues
Author-email: "Ion Cicala (Nextron Systems GmbH)" <ion.cicala@nextron-systems.com>
License: MIT
License-File: LICENSE
Keywords: nextron,thor,thor2timesketch,thor2ts,timesketch
Classifier: Development Status :: 2 - Pre-Alpha
Classifier: Environment :: Console
Classifier: License :: OSI Approved :: MIT License
Classifier: Operating System :: OS Independent
Classifier: Programming Language :: Python :: 3
Requires-Python: >=3.9
Requires-Dist: python-dateutil~=2.9.0.post0
Requires-Dist: pyyaml~=6.0.2
Requires-Dist: rich~=14.0.0
Requires-Dist: timesketch-import-client
Requires-Dist: typer~=0.15.2
Requires-Dist: types-python-dateutil
Provides-Extra: dev
Requires-Dist: black; extra == 'dev'
Requires-Dist: mypy; extra == 'dev'
Requires-Dist: pytest; extra == 'dev'
Requires-Dist: ruff; extra == 'dev'
Requires-Dist: types-pyyaml; extra == 'dev'
Provides-Extra: publish
Requires-Dist: build; extra == 'publish'
Requires-Dist: hatch-vcs; extra == 'publish'
Requires-Dist: twine; extra == 'publish'
